pandas_plink/__init__.py
pandas_plink/_allele.py
pandas_plink/_bed_read.py
pandas_plink/_bed_reader.c
pandas_plink/_bed_reader.h
pandas_plink/_bed_write.py
pandas_plink/_bed_writer.c
pandas_plink/_bed_writer.h
pandas_plink/_chunk.py
pandas_plink/_data.py
pandas_plink/_filetype.py
pandas_plink/_read.py
pandas_plink/_read_grm.py
pandas_plink/_read_rel.py
pandas_plink/_testit.py
pandas_plink/_type.py
pandas_plink/_util.py
pandas_plink/_write.py
pandas_plink/bed_reader.cp310-win_amd64.pyd
pandas_plink/bed_reader.cp311-win_amd64.pyd
pandas_plink/conftest.py
pandas_plink-2.3.1.dist-info/LICENSE.md
pandas_plink-2.3.1.dist-info/METADATA
pandas_plink-2.3.1.dist-info/WHEEL
pandas_plink-2.3.1.dist-info/RECORD
