Metadata-Version: 2.1
Name: pandas-plink
Version: 2.3.1
Summary: Read PLINK files into Pandas data frames
Home-page: https://github.com/limix/pandas-plink
License: MIT
Keywords: plink,reader,genetics
Author: Danilo Horta
Author-email: danilo.horta@pm.me
Requires-Python: >=3.10,<4.0
Classifier: License :: OSI Approved :: MIT License
Classifier: Programming Language :: Python :: 3
Classifier: Programming Language :: Python :: 3.10
Classifier: Programming Language :: Python :: 3.11
Classifier: Programming Language :: Python :: 3.12
Requires-Dist: cffi (>=1.16,<2.0)
Requires-Dist: dask[dataframe]
Requires-Dist: deprecated (>=1.2,<2.0)
Requires-Dist: numpy (>=1.0,<2.0)
Requires-Dist: pandas (>=2.2,<3.0)
Requires-Dist: pandera[dask,mypy]
Requires-Dist: tqdm (>=4.66,<5.0)
Requires-Dist: xarray
Requires-Dist: zstandard (>=0.22,<0.23)
Project-URL: Repository, https://github.com/limix/pandas-plink
